txhlf/__init__.py
txhlf/constants.py
txhlf/tx_hlf.py
txhlf-0.2.dist-info/LICENSE.txt
txhlf-0.2.dist-info/METADATA
txhlf-0.2.dist-info/WHEEL
txhlf-0.2.dist-info/top_level.txt
txhlf-0.2.dist-info/RECORD
