Metadata-Version: 2.1
Name: txhlf
Version: 0.2
Summary: txhlf is the official Python SDK for Traxion HLF
Home-page: https://github.com/jaarce/txhlf
Author: JA Arce
Author-email: johnandrewarce@gmail.com
License: BSD
Keywords: txhlf
Platform: UNKNOWN
Classifier: Topic :: Utilities
Classifier: Environment :: Web Environment
Classifier: License :: OSI Approved :: BSD License
Requires-Python: >=3.0
Requires-Dist: requests (==2.21.0)
